tracktotrip3/__init__.py
tracktotrip3/classifier.py
tracktotrip3/compression.py
tracktotrip3/kalman.py
tracktotrip3/learn_trip.py
tracktotrip3/location.py
tracktotrip3/point.py
tracktotrip3/segment.py
tracktotrip3/similarity.py
tracktotrip3/smooth.py
tracktotrip3/spatiotemporal_segmentation.py
tracktotrip3/track.py
tracktotrip3/transportation_mode.py
tracktotrip3/utils.py
tracktotrip3-0.1.1.data/scripts/tracktotrip_geolife_dataset
tracktotrip3-0.1.1.data/scripts/tracktotrip_util
tracktotrip3-0.1.1.dist-info/LICENSE
tracktotrip3-0.1.1.dist-info/METADATA
tracktotrip3-0.1.1.dist-info/WHEEL
tracktotrip3-0.1.1.dist-info/top_level.txt
tracktotrip3-0.1.1.dist-info/RECORD
