Metadata-Version: 2.1
Name: tracktotrip3
Version: 0.1.1
Summary: Track processing library for Python 3
Home-page: https://github.com/dserafim1999/tracktotrip3
Download-URL: https://github.com/dserafim1999/tracktotrip3/releases/tag/0.1.1
Author: Daniel Serafim, Rui Gil
Author-email: dserafim1999@gmail.com
Keywords: track,trip,GPS,GPX
License-File: LICENSE
Requires-Dist: certifi (==2022.5.18.1)
Requires-Dist: changepy (==0.3.1)
Requires-Dist: charset-normalizer (==2.0.12)
Requires-Dist: gpxpy (==1.5.0)
Requires-Dist: idna (==3.3)
Requires-Dist: ikalman (==0.2.0)
Requires-Dist: joblib (==1.1.0)
Requires-Dist: numpy (==1.22.3)
Requires-Dist: requests (==2.27.1)
Requires-Dist: Rtree (==1.0.0)
Requires-Dist: rtreelib (==0.2.0)
Requires-Dist: scikit-learn (==1.1.1)
Requires-Dist: scipy (==1.8.1)
Requires-Dist: sklearn (==0.0)
Requires-Dist: threadpoolctl (==3.1.0)
Requires-Dist: urllib3 (==1.26.9)
